tarot_cmoney/.DS_Store
tarot_cmoney/__init__.py
tarot_cmoney/card.py
tarot_cmoney/cards/Cups10.json
tarot_cmoney/cards/Cups2.json
tarot_cmoney/cards/Cups3.json
tarot_cmoney/cards/Cups4.json
tarot_cmoney/cards/Cups5.json
tarot_cmoney/cards/Cups6.json
tarot_cmoney/cards/Cups7.json
tarot_cmoney/cards/Cups8.json
tarot_cmoney/cards/Cups9.json
tarot_cmoney/cards/CupsAce.json
tarot_cmoney/cards/CupsKing.json
tarot_cmoney/cards/CupsKnight.json
tarot_cmoney/cards/CupsPage.json
tarot_cmoney/cards/CupsQueen.json
tarot_cmoney/cards/Death.json
tarot_cmoney/cards/Judgement.json
tarot_cmoney/cards/Justice.json
tarot_cmoney/cards/Pentacles10.json
tarot_cmoney/cards/Pentacles2.json
tarot_cmoney/cards/Pentacles3.json
tarot_cmoney/cards/Pentacles4.json
tarot_cmoney/cards/Pentacles5.json
tarot_cmoney/cards/Pentacles6.json
tarot_cmoney/cards/Pentacles7.json
tarot_cmoney/cards/Pentacles8.json
tarot_cmoney/cards/Pentacles9.json
tarot_cmoney/cards/PentaclesAce.json
tarot_cmoney/cards/PentaclesKing.json
tarot_cmoney/cards/PentaclesKnight.json
tarot_cmoney/cards/PentaclesPage.json
tarot_cmoney/cards/PentaclesQueen.json
tarot_cmoney/cards/Strength.json
tarot_cmoney/cards/Swords10.json
tarot_cmoney/cards/Swords2.json
tarot_cmoney/cards/Swords3.json
tarot_cmoney/cards/Swords4.json
tarot_cmoney/cards/Swords5.json
tarot_cmoney/cards/Swords6.json
tarot_cmoney/cards/Swords7.json
tarot_cmoney/cards/Swords8.json
tarot_cmoney/cards/Swords9.json
tarot_cmoney/cards/SwordsAce.json
tarot_cmoney/cards/SwordsKing.json
tarot_cmoney/cards/SwordsKnight.json
tarot_cmoney/cards/SwordsPage.json
tarot_cmoney/cards/SwordsQueen.json
tarot_cmoney/cards/Temperance.json
tarot_cmoney/cards/TheChariot.json
tarot_cmoney/cards/TheDevil.json
tarot_cmoney/cards/TheEmperor.json
tarot_cmoney/cards/TheEmpress.json
tarot_cmoney/cards/TheFool.json
tarot_cmoney/cards/TheHangedMan.json
tarot_cmoney/cards/TheHermit.json
tarot_cmoney/cards/TheHierophant.json
tarot_cmoney/cards/TheHighPriestess.json
tarot_cmoney/cards/TheLovers.json
tarot_cmoney-0.1.5.dist-info/METADATA
tarot_cmoney-0.1.5.dist-info/WHEEL
tarot_cmoney-0.1.5.dist-info/RECORD
