Metadata-Version: 2.1
Name: tarot-cmoney
Version: 0.1.5
Summary: 
Author: christian.phillips
Author-email: phristianchillips@gmail.com
Requires-Python: >=3.12,<4.0
Classifier: Programming Language :: Python :: 3
Classifier: Programming Language :: Python :: 3.12
Classifier: Programming Language :: Python :: 3.13
Requires-Dist: openai (>=1.57.3,<2.0.0)
